factors/__init__.py
factors/factors.py
math_factors-1.0.2.dist-info/LICENSE
math_factors-1.0.2.dist-info/METADATA
math_factors-1.0.2.dist-info/WHEEL
math_factors-1.0.2.dist-info/entry_points.txt
math_factors-1.0.2.dist-info/top_level.txt
math_factors-1.0.2.dist-info/zip-safe
math_factors-1.0.2.dist-info/RECORD
