Metadata-Version: 2.1
Name: math-factors
Version: 1.0.2
Summary: Demo Package for Mathematical Factors.
Home-page: https://github.com/Prateek23n/Factors
Author: Prateek C. Tripathi
Author-email: prateektripathi85@gmail.com
License: MIT
Keywords: python factors
Platform: UNKNOWN
Classifier: Development Status :: 3 - Alpha
Classifier: Intended Audience :: Developers
Classifier: Topic :: Software Development :: Build Tools
Classifier: License :: OSI Approved :: MIT License
Classifier: Programming Language :: Python :: 2
Classifier: Programming Language :: Python :: 2.6
Classifier: Programming Language :: Python :: 2.7
Classifier: Programming Language :: Python :: 3
Classifier: Programming Language :: Python :: 3.2
Classifier: Programming Language :: Python :: 3.3
Classifier: Programming Language :: Python :: 3.4
Classifier: Programming Language :: Python :: 3.5
Classifier: Programming Language :: Python :: 3.6
Classifier: Programming Language :: Python :: 3.7
Requires-Python: >=2.6, !=3.0.*, !=3.1.*, !=3.2.*, <4
